Workbook

Sheet Output
A1: Year ID | B1: Year | C1: Student_ID | D1: Gender_ID | E1: Enrollment_Date | F1: Course_Name_ID | G1: Start_Date | H1: End_Date | I1: Course_Duration_ID | J1: Category_ID | K1: Course_Fee | L1: Trainer_ID | M1: Trainer_Fee | N1: Experience_Years | O1: Status_ID | P1: Teaching_Mode_ID | Q1: Teaching_Desciption_ID | R1: Key_Features_ID | S1: Stationery Fees | T1: Admission_Source_ID | U1: Lead Per Cost | V1: Operating Cost | W1: Team_Lead_ID | X1: Total Fees | Y1: Total Cost | Z1: Gross Profit | AA1: Course Duration (Days) | AB1: Hierarchy_UID | AC1: Student_Level_Hierarchy
A2: =_xlfn.XLOOKUP(E2,Date_Dim!B:B,Date_Dim!A:A) -> 1 | B2: 2022 | C2: 1 | D2: 2 | E2: 45113 | F2: 1 | G2: 45143 | H2: 45157 | I2: 1 | J2: 1 | K2: 1459 | L2: 1 | M2: 3000 | N2: 15 | O2: 1 | P2: 1 | Q2: 1 | R2: 1 | S2: 0 | T2: 1 | U2: 0 | V2: 1783.6 | W2: 1 | X2: 4459 | Y2: =M2+U2+V2 -> 4783.6 | Z2: =X2-Y2 -> -324.6 | AA2: =H2-G2 -> 14 | AB2: =P2&J2&T2&F2 -> 1111 | AC2: =P2&"1"&J2&"1"&T2&"1"&F2 -> 1111111
A3: =_xlfn.XLOOKUP(E3,Date_Dim!B:B,Date_Dim!A:A) -> 2 | B3: 2020 | C3: 2 | D3: 2 | E3: 44697 | F3: 2 | G3: 44727 | H3: 44769 | I3: 4 | J3: 2 | K3: 1999 | L3: 2 | M3: 4000 | N3: 14 | O3: 1 | P3: 1 | Q3: 1 | R3: 1 | S3: 0 | T3: 2 | U3: 175 | V3: 2399.6 | W3: 2 | X3: 5999 | Y3: =M3+U3+V3 -> 6574.6 | Z3: =X3-Y3 -> -575.6 | AA3: =H3-G3 -> 42 | AB3: =P3&J3&T3&F3 -> 1222 | AC3: =P3&"1"&J3&"1"&T3&"1"&F3 -> 1121212
A4: =_xlfn.XLOOKUP(E4,Date_Dim!B:B,Date_Dim!A:A) -> 3 | B4: 2023 | C4: 2 | D4: 2 | E4: 45072 | F4: 3 | G4: 45102 | H4: 45130 | I4: 3 | J4: 3 | K4: 1689 | L4: 3 | M4: 2000 | N4: 12 | O4: 1 | P4: 1 | Q4: 1 | R4: 1 | S4: 0 | T4: 2 | U4: 175 | V4: 1106.7 | W4: 2 | X4: 3689 | Y4: =M4+U4+V4 -> 3281.7 | Z4: =X4-Y4 -> 407.3 | AA4: =H4-G4 -> 28 | AB4: =P4&J4&T4&F4 -> 1323 | AC4: =P4&"1"&J4&"1"&T4&"1"&F4 -> 1131213
A5: =_xlfn.XLOOKUP(E5,Date_Dim!B:B,Date_Dim!A:A) -> 4 | B5: 2021 | C5: 3 | D5: 2 | E5: 45511 | F5: 4 | G5: 45541 | H5: 45555 | I5: 1 | J5: 2 | K5: 1459 | L5: 4 | M5: 1000 | N5: 5 | O5: 1 | P5: 2 | Q5: 2 | R5: 2 | S5: 6000 | T5: 2 | U5: 175 | V5: 3383.6 | W5: 3 | X5: 8459 | Y5: =M5+U5+V5 -> 4558.6 | Z5: =X5-Y5 -> 3900.4 | AA5: =H5-G5 -> 14 | AB5: =P5&J5&T5&F5 -> 2224 | AC5: =P5&"1"&J5&"1"&T5&"1"&F5 -> 2121214
A6: =_xlfn.XLOOKUP(E6,Date_Dim!B:B,Date_Dim!A:A) -> 5 | B6: 2021 | C6: 4 | D6: 2 | E6: 44194 | F6: 5 | G6: 44224 | H6: 44280 | I6: 5 | J6: 4 | K6: 2699 | L6: 5 | M6: 5000 | N6: 8 | O6: 1 | P6: 3 | Q6: 3 | R6: 3 | S6: 2000 | T6: 3 | U6: 125 | V6: 2909.7 | W6: 4 | X6: 9699 | Y6: =M6+U6+V6 -> 8034.7 | Z6: =X6-Y6 -> 1664.3 | AA6: =H6-G6 -> 56 | AB6: =P6&J6&T6&F6 -> 3435 | AC6: =P6&"1"&J6&"1"&T6&"1"&F6 -> 3141315
A7: =_xlfn.XLOOKUP(E7,Date_Dim!B:B,Date_Dim!A:A) -> 6 | B7: 2024 | C7: 4 | D7: 2 | E7: 45128 | F7: 6 | G7: 45158 | H7: 45200 | I7: 4 | J7: 4 | K7: 1999 | L7: 6 | M7: 3000 | N7: 9 | O7: 1 | P7: 4 | Q7: 4 | R7: 4 | S7: 0 | T7: 4 | U7: 135 | V7: 1499.7 | W7: 5 | X7: 4999 | Y7: =M7+U7+V7 -> 4634.7 | Z7: =X7-Y7 -> 364.3 | AA7: =H7-G7 -> 42 | AB7: =P7&J7&T7&F7 -> 4446 | AC7: =P7&"1"&J7&"1"&T7&"1"&F7 -> 4141416
A8: =_xlfn.XLOOKUP(E8,Date_Dim!B:B,Date_Dim!A:A) -> 7 | B8: 2021 | C8: 5 | D8: 2 | E8: 45063 | F8: 7 | G8: 45093 | H8: 45114 | I8: 2 | J8: 3 | K8: 1559 | L8: 7 | M8: 1500 | N8: 1 | O8: 1 | P8: 1 | Q8: 1 | R8: 1 | S8: 0 | T8: 2 | U8: 175 | V8: 917.7 | W8: 2 | X8: 3059 | Y8: =M8+U8+V8 -> 2592.7 | Z8: =X8-Y8 -> 466.3 | AA8: =H8-G8 -> 21 | AB8: =P8&J8&T8&F8 -> 1327 | AC8: =P8&"1"&J8&"1"&T8&"1"&F8 -> 1131217
A9: =_xlfn.XLOOKUP(E9,Date_Dim!B:B,Date_Dim!A:A) -> 8 | B9: 2024 | C9: 5 | D9: 2 | E9: 44306 | F9: 8 | G9: 44336 | H9: 44350 | I9: 1 | J9: 4 | K9: 1459 | L9: 8 | M9: 1800 | N9: 2 | O9: 1 | P9: 4 | Q9: 4 | R9: 4 | S9: 0 | T9: 5 | U9: 155 | V9: 977.7 | W9: 6 | X9: 3259 | Y9: =M9+U9+V9 -> 2932.7 | Z9: =X9-Y9 -> 326.3 | AA9: =H9-G9 -> 14 | AB9: =P9&J9&T9&F9 -> 4458 | AC9: =P9&"1"&J9&"1"&T9&"1"&F9 -> 4141518
A10: =_xlfn.XLOOKUP(E10,Date_Dim!B:B,Date_Dim!A:A) -> 9 | B10: 2024 | C10: 6 | D10: 2 | E10: 44811 | F10: 9 | G10: 44841 | H10: 44897 | I10: 5 | J10: 3 | K10: 2699 | L10: 3 | M10: 3500 | N10: 12 | O10: 1 | P10: 1 | Q10: 1 | R10: 1 | S10: 0 | T10: 6 | U10: 120 | V10: 2479.6 | W10: 1 | X10: 6199 | Y10: =M10+U10+V10 -> 6099.6 | Z10: =X10-Y10 -> 99.4 | AA10: =H10-G10 -> 56 | AB10: =P10&J10&T10&F10 -> 1369 | AC10: =P10&"1"&J10&"1"&T10&"1"&F10 -> 1131619
A11: =_xlfn.XLOOKUP(E11,Date_Dim!B:B,Date_Dim!A:A) -> 10 | B11: 2021 | C11: 6 | D11: 2 | E11: 44625 | F11: 6 | G11: 44655 | H11: 44697 | I11: 4 | J11: 4 | K11: 1999 | L11: 6 | M11: 3000 | N11: 9 | O11: 1 | P11: 3 | Q11: 3 | R11: 3 | S11: 2000 | T11: 4 | U11: 135 | V11: 2099.7 | W11: 7 | X11: 6999 | Y11: =M11+U11+V11 -> 5234.7 | Z11: =X11-Y11 -> 1764.3 | AA11: =H11-G11 -> 42 | AB11: =P11&J11&T11&F11 -> 3446 | AC11: =P11&"1"&J11&"1"&T11&"1"&F11 -> 3141416
A12: =_xlfn.XLOOKUP(E12,Date_Dim!B:B,Date_Dim!A:A) -> 11 | B12: 2022 | C12: 7 | D12: 2 | E12: 45107 | F12: 10 | G12: 45137 | H12: 45151 | I12: 1 | J12: 5 | K12: 1459 | L12: 9 | M12: 1000 | N12: 4 | O12: 1 | P12: 4 | Q12: 4 | R12: 4 | S12: 0 | T12: 5 | U12: 155 | V12: 737.7 | W12: 8 | X12: 2459 | Y12: =M12+U12+V12 -> 1892.7 | Z12: =X12-Y12 -> 566.3 | AA12: =H12-G12 -> 14 | AB12: =P12&J12&T12&F12 -> 45510 | AC12: =P12&"1"&J12&"1"&T12&"1"&F12 -> 41515110
A13: =_xlfn.XLOOKUP(E13,Date_Dim!B:B,Date_Dim!A:A) -> 12 | B13: 2021 | C13: 8 | D13: 2 | E13: 44780 | F13: 6 | G13: 44810 | H13: 44852 | I13: 4 | J13: 4 | K13: 1999 | L13: 6 | M13: 3000 | N13: 9 | O13: 1 | P13: 3 | Q13: 3 | R13: 3 | S13: 2000 | T13: 4 | U13: 135 | V13: 2099.7 | W13: 7 | X13: 6999 | Y13: =M13+U13+V13 -> 5234.7 | Z13: =X13-Y13 -> 1764.3 | AA13: =H13-G13 -> 42 | AB13: =P13&J13&T13&F13 -> 3446 | AC13: =P13&"1"&J13&"1"&T13&"1"&F13 -> 3141416
... A350: =_xlfn.XLOOKUP(E350,Date_Dim!B:B,Date_Dim!A:A) -> 310 | B350: 2021 | C350: 215 | D350: 2 | E350: 44092 | F350: 15 | G350: 44122 | H350: 44150 | I350: 3 | J350: 2 | K350: 1689 | L350: 10 | M350: 2500 | N350: 6 | O350: 1 | P350: 2 | Q350: 2 | R350: 2 | S350: 6000 | T350: 2 | U350: 175 | V350: 3056.7 | W350: 3 | X350: 10189 | Y350: =M350+U350+V350 -> 5731.7 | Z350: =X350-Y350 -> 4457.3 | AA350: =H350-G350 -> 28 | AB350: =P350&J350&T350&F350 -> 22215 | AC350: =P350&"1"&J350&"1"&T350&"1"&F350 -> 21212115

Sheet Sheet1
A1: Column Name | B1: Description | D1: Column Name | E1: Description | G1: Column Name | H1: Description | J1: Column Name | K1: Description
A2: Student_ID | B2: Unique identifier for each student | D2: Hierarchy_UID | E2: Unique hierarchy key | G2: Student_ID | H2: Unique student key | J2: Key_Features_ID | K2: Unique ID for feature set
A3: Gender_ID | B3: Foreign key linked to student's gender | D3: Teaching_Mode_ID | E3: Mode of teaching (Online/Offline/Hybrid) | G3: Student_Name | H3: Full name of the student | J3: Key Features of Teaching | K3: Key USPs or training highlights
A4: Enrollment_Date | B4: Date when the student enrolled | D4: Category_ID | E4: Course category ID
A5: Course_Name_ID | B5: Foreign key for course name | D5: Admission_Source_ID | E5: Source through which student was acquired | G5: Column Name | H5: Description | J5: From (Fact Table) | K5: To (Dimension Table) | L5: Key Field | M5: Cardinality
A6: Start_Date / End_Date | B6: Actual start and end date of course | D6: Course_Name_ID | E6: Name of the course | G6: Gender_ID | H6: Unique gender key | J6: Output.Student_ID | K6: Student_Dim.Student_ID | L6: Student_ID | M6: Many to One (*)
A7: Course_Duration_ID | B7: Foreign key for course duration | D7: Teaching Mode | E7: Mode in readable format | G7: Student_Gender | H7: Gender label (Male/Female) | J7: Output.Course_Name_ID | K7: Hierarchy_Dim.Course_Name_ID | L7: Course_Name_ID | M7: Many to One (*)
A8: Category_ID | B8: Foreign key for course category | D8: Course_Category | E8: High-level category of course | J8: Output.Date | K8: Date_Dim.Date | L8: Start_Date / Enrollment | M8: Many to One (*)
A9: Course_Fee | B9: Total fee charged for the course | D9: Admission Source | E9: Name of marketing source | G9: Column Name | H9: Description | J9: Output.Trainer_ID | K9: Trainer_Dim.Trainer_ID | L9: Trainer_ID | M9: Many to One (*)
A10: Trainer_ID | B10: Foreign key for assigned trainer | D10: Course_Name | E10: Full name of course | G10: Course_Duration_ID | H10: Unique duration ID | J10: Output.Status_ID | K10: Status_Dim.Status_ID | L10: Status_ID | M10: Many to One (*)
A11: Trainer_Fee | B11: Amount paid to the trainer | G11: Course_Duration | H11: Duration in weeks/months | J11: Output.Gender_ID | K11: Gender_Dim.Gender_ID | L11: Gender_ID | M11: Many to One (*)
A12: Experience_Years | B12: Trainer's years of experience | D12: Column Name | E12: Description | J12: Output.Team_Lead_ID | K12: Team_Lead_Dim.Team_Lead_ID | L12: Team_Lead_ID | M12: Many to One (*)
A13: Status_ID | B13: Current course status (Active, Completed) | D13: UID | E13: Unique record ID | G13: Column Name | H13: Description | J13: Output.Key_Features_ID | K13: Key_Features_Training_Dim.Key_Features_ID | L13: Key_Features_ID | M13: Many to One (*)
A14: Teaching_Mode_ID | B14: Mode of teaching (Online, Offline, Hybrid) | D14: Teaching_Mode_ID | E14: Mode of teaching | G14: Trainer_ID | H14: Unique trainer key
A15: Teaching_Desciption_ID | B15: Extra detail about the teaching style | D15: Category_ID | E15: Course category | G15: Trainer_Name | H15: Trainer's full name
A16: Key_Features_ID | B16: Highlights or features of the training | D16: Admission_Source_ID | E16: Source of admission
A17: Stationery Fees | B17: Additional stationery charges | D17: Course_Name_ID | E17: Course identifier | G17: Column Name | H17: Description
A18: Admission_Source_ID | B18: Source of admission (online ads, referral, etc.) | D18: Student_ID | E18: Student assigned to the course | G18: Status_ID | H18: Course status key
A19: Lead Per Cost | B19: Cost per lead for student acquisition | G19: Status | H19: Course status (Active/Completed)
A20: Operating Cost | B20: Operational expense for running the batch | D20: Column Name | E20: Description
A21: Team_Lead_ID | B21: Assigned team leader | D21: Date_ID | E21: Unique date key | G21: Column Name | H21: Description
A22: Total Fees | B22: Total of all fees paid by student | D22: Date | E22: Full date value | G22: Teaching_Desciption_ID | H22: ID for teaching approach style
A23: Total Cost | B23: Combined cost (trainer + stationery + operations) | D23: Year | E23: Year component | G23: Teaching Description | H23: Description of how it's taught
A24: Gross Profit | B24: Profit earned = Total Fees - Total Cost | D24: Short Month | E24: Abbreviated month name (e.g., Jan)
A25: Course Duration (Days) | B25: Duration of course in days | D25: Month | E25: Full month name | G25: Column Name | H25: Description
A26: Hierarchy_UID | B26: Composite key to join dimension | G26: Team_Lead_ID | H26: Unique team lead key
A27: Student_Level_Hierarchy | B27: Custom hierarchy level of student | G27: Team_Lead | H27: Name of the team lead

Sheet Hierarchy_Dim
A1: Hierarchy_UID | B1: Teaching_Mode_ID | C1: Category_ID | D1: Admission_Source_ID | E1: Course_Name_ID | F1: Teaching Mode | G1: Course_Category | H1: Admission Source | I1: Course_Name
A2: =B2&C2&D2&E2 -> 1111 | B2: 1 | C2: 1 | D2: 1 | E2: 1 | F2: Online Live Classes | G2: Financial Planning and Management | H2: Walk-Ins | I2: Personal Financial Planning
A3: =B3&C3&D3&E3 -> 1222 | B3: 1 | C3: 2 | D3: 2 | E3: 2 | F3: Online Live Classes | G3: Data Analytics and Visualization | H3: Social Media | I3: Data Cleaning and Preprocessing
A4: =B4&C4&D4&E4 -> 1323 | B4: 1 | C4: 3 | D4: 2 | E4: 3 | F4: Online Live Classes | G4: Digital Marketing and Transformation | H4: Social Media | I4: Introduction to Digital Marketing
A5: =B5&C5&D5&E5 -> 2224 | B5: 2 | C5: 2 | D5: 2 | E5: 4 | F5: Classroom-Based Learning | G5: Data Analytics and Visualization | H5: Social Media | I5: Google Analytics for Beginners
A6: =B6&C6&D6&E6 -> 3435 | B6: 3 | C6: 4 | D6: 3 | E6: 5 | F6: Blended Learning | G6: Stock Market and Investment | H6: Data Calling | I6: Equity Research Analysis
A7: =B7&C7&D7&E7 -> 4446 | B7: 4 | C7: 4 | D7: 4 | E7: 6 | F7: Self-Paced Learning | G7: Stock Market and Investment | H7: Google Ads | I7: Technical Analysis of Stocks
A8: =B8&C8&D8&E8 -> 1327 | B8: 1 | C8: 3 | D8: 2 | E8: 7 | F8: Online Live Classes | G8: Digital Marketing and Transformation | H8: Social Media | I8: Content Marketing
A9: =B9&C9&D9&E9 -> 4458 | B9: 4 | C9: 4 | D9: 5 | E9: 8 | F9: Self-Paced Learning | G9: Stock Market and Investment | H9: YouTube Ads | I9: Stock Market Basics
A10: =B10&C10&D10&E10 -> 1369 | B10: 1 | C10: 3 | D10: 6 | E10: 9 | F10: Online Live Classes | G10: Digital Marketing and Transformation | H10: Referrals | I10: Search Engine Optimization (SEO)
A11: =B11&C11&D11&E11 -> 3446 | B11: 3 | C11: 4 | D11: 4 | E11: 6 | F11: Blended Learning | G11: Stock Market and Investment | H11: Google Ads | I11: Technical Analysis of Stocks
A12: =B12&C12&D12&E12 -> 45510 | B12: 4 | C12: 5 | D12: 5 | E12: 10 | F12: Self-Paced Learning | G12: Financial Technology (FinTech) | H12: YouTube Ads | I12: Introduction to FinTech
A13: =B13&C13&D13&E13 -> 22211 | B13: 2 | C13: 2 | D13: 2 | E13: 11 | F13: Classroom-Based Learning | G13: Data Analytics and Visualization | H13: Social Media | I13: Power BI Basics
... A53: =B53&C53&D53&E53 -> 1329 | B53: 1 | C53: 3 | D53: 2 | E53: 9 | F53: Online Live Classes | G53: Digital Marketing and Transformation | H53: Social Media | I53: Search Engine Optimization (SEO)

Sheet Student_level_Hierarchy
A1: UID | B1: Teaching_Mode_ID | C1: Category_ID | D1: Admission_Source_ID | E1: Course_Name_ID | F1: Student_ID
A2: =B2&"1"&C2&"1"&D2&"1"&E2&"1"&F2 -> 111111111 | B2: 1 | C2: 1 | D2: 1 | E2: 1 | F2: 1
A3: =B3&"1"&C3&"1"&D3&"1"&E3&"1"&F3 -> 112121212 | B3: 1 | C3: 2 | D3: 2 | E3: 2 | F3: 2
A4: =B4&"1"&C4&"1"&D4&"1"&E4&"1"&F4 -> 113121312 | B4: 1 | C4: 3 | D4: 2 | E4: 3 | F4: 2
A5: =B5&"1"&C5&"1"&D5&"1"&E5&"1"&F5 -> 212121413 | B5: 2 | C5: 2 | D5: 2 | E5: 4 | F5: 3
A6: =B6&"1"&C6&"1"&D6&"1"&E6&"1"&F6 -> 314131514 | B6: 3 | C6: 4 | D6: 3 | E6: 5 | F6: 4
A7: =B7&"1"&C7&"1"&D7&"1"&E7&"1"&F7 -> 414141614 | B7: 4 | C7: 4 | D7: 4 | E7: 6 | F7: 4
A8: =B8&"1"&C8&"1"&D8&"1"&E8&"1"&F8 -> 113121715 | B8: 1 | C8: 3 | D8: 2 | E8: 7 | F8: 5
A9: =B9&"1"&C9&"1"&D9&"1"&E9&"1"&F9 -> 414151815 | B9: 4 | C9: 4 | D9: 5 | E9: 8 | F9: 5
A10: =B10&"1"&C10&"1"&D10&"1"&E10&"1"&F10 -> 113161916 | B10: 1 | C10: 3 | D10: 6 | E10: 9 | F10: 6
A11: =B11&"1"&C11&"1"&D11&"1"&E11&"1"&F11 -> 314141616 | B11: 3 | C11: 4 | D11: 4 | E11: 6 | F11: 6
A12: =B12&"1"&C12&"1"&D12&"1"&E12&"1"&F12 -> 4151511017 | B12: 4 | C12: 5 | D12: 5 | E12: 10 | F12: 7
A13: =B13&"1"&C13&"1"&D13&"1"&E13&"1"&F13 -> 314141618 | B13: 3 | C13: 4 | D13: 4 | E13: 6 | F13: 8
... A351: =B351&"1"&C351&"1"&D351&"1"&E351&"1"&F351 -> 411181211215 | B351: 4 | C351: 1 | D351: 8 | E351: 21 | F351: 215

Sheet Date_Dim
A1: Date_ID | B1: Date | C1: year | D1: Short month | E1: Month
A2: 1 | B2: 45113 | C2: =YEAR(B2) -> 2023 | D2: =TEXT(B2,"MMM") -> Jul | E2: =MONTH(B2) -> 7
A3: 2 | B3: 44697 | C3: =YEAR(B3) -> 2022 | D3: =TEXT(B3,"MMM") -> May | E3: =MONTH(B3) -> 5
A4: 3 | B4: 45072 | C4: =YEAR(B4) -> 2023 | D4: =TEXT(B4,"MMM") -> May | E4: =MONTH(B4) -> 5
A5: 4 | B5: 45511 | C5: =YEAR(B5) -> 2024 | D5: =TEXT(B5,"MMM") -> Aug | E5: =MONTH(B5) -> 8
A6: 5 | B6: 44194 | C6: =YEAR(B6) -> 2020 | D6: =TEXT(B6,"MMM") -> Dec | E6: =MONTH(B6) -> 12
A7: 6 | B7: 45128 | C7: =YEAR(B7) -> 2023 | D7: =TEXT(B7,"MMM") -> Jul | E7: =MONTH(B7) -> 7
A8: 7 | B8: 45063 | C8: =YEAR(B8) -> 2023 | D8: =TEXT(B8,"MMM") -> May | E8: =MONTH(B8) -> 5
A9: 8 | B9: 44306 | C9: =YEAR(B9) -> 2021 | D9: =TEXT(B9,"MMM") -> Apr | E9: =MONTH(B9) -> 4
A10: 9 | B10: 44811 | C10: =YEAR(B10) -> 2022 | D10: =TEXT(B10,"MMM") -> Sep | E10: =MONTH(B10) -> 9
A11: 10 | B11: 44625 | C11: =YEAR(B11) -> 2022 | D11: =TEXT(B11,"MMM") -> Mar | E11: =MONTH(B11) -> 3
A12: 11 | B12: 45107 | C12: =YEAR(B12) -> 2023 | D12: =TEXT(B12,"MMM") -> Jun | E12: =MONTH(B12) -> 6
A13: 12 | B13: 44780 | C13: =YEAR(B13) -> 2022 | D13: =TEXT(B13,"MMM") -> Aug | E13: =MONTH(B13) -> 8
... A311: 310 | B311: 44092 | C311: =YEAR(B311) -> 2020 | D311: =TEXT(B311,"MMM") -> Sep | E311: =MONTH(B311) -> 9

Sheet Student_Dim
A1: Student_ID | B1: Student_Name
A2: 1 | B2: Aaina Aggarwal
A3: 2 | B3: Aaina Apte
A4: 3 | B4: Aaina Babu
A5: 4 | B5: Aaina Banerjee
A6: 5 | B6: Aaina Brahmbhatt
A7: 6 | B7: Aaina Butala
A8: 7 | B8: Aaina Choudhry
A9: 8 | B9: Aaina Choudhury
A10: 9 | B10: Aaina D’Alia
A11: 10 | B11: Aaina Dave
A12: 11 | B12: Aaina Dayal
A13: 12 | B13: Aaina Din
... A216: 215 | B216: Aaryahi Srinivas

Sheet Gender_Dim
A1: Gender_ID | B1: Student_Gender
A2: 1 | B2: Male
A3: 2 | B3: Female

Sheet Course_Duration_Dim
A1: Course_Duration_ID | B1: Course_Duration
A2: 1 | B2: 2 Weeks
A3: 2 | B3: 3 Weeks
A4: 3 | B4: 4 Weeks
A5: 4 | B5: 6 Weeks
A6: 5 | B6: 8 Weeks

Sheet Trainer_Dim
A1: Trainer_ID | B1: Trainer_Name
A2: 1 | B2: Raushan Sharma
A3: 2 | B3: Priya Iyer
A4: 3 | B4: Siddharth Ranjan
A5: 4 | B5: Sanket Barmecha
A6: 5 | B6: Nikhil Malhotra
A7: 6 | B7: Neelima Ranjan
A8: 7 | B8: Rohit Chaudhary
A9: 8 | B9: Piyush Kumar
A10: 9 | B10: Pooja Patel
A11: 10 | B11: Kunal Gupta
A12: 11 | B12: Manish Raj
A13: 12 | B13: Neha Shah
... A17: 16 | B17: Sumeet Rajput

Sheet Status_Dim
A1: Status_ID | B1: Status
A2: 1 | B2: Completed
A3: 2 | B3: Active

Sheet Teaching_Description_Dim
A1: Teaching_Desciption_ID | B1: Teaching Description
A2: 1 | B2: Real-time virtual teaching using platforms like Zoom or Google Meet.
A3: 2 | B3: Traditional in-person teaching in a physical classroom.
A4: 3 | B4: Combines in-person and online teaching methods.
A5: 4 | B5: Pre-recorded courses accessible anytime, anywhere.
A6: 5 | B6: Hands-on training focusing on practical projects or problem-solving tasks.

Sheet Team_Lead_Dim
A1: Team_Lead_ID | B1: Team_Lead
A2: 1 | B2: Arjun Patel
A3: 2 | B3: Priya Mehta
A4: 3 | B4: Rohan Sharma
A5: 4 | B5: Nidhi Jaiswal
A6: 5 | B6: Kavya Gupta
A7: 6 | B7: Ankit Verma
A8: 7 | B8: Vinay Pandey
A9: 8 | B9: Sneha Kapoor
A10: 9 | B10: Akshay Pandey

Sheet Key_Features_Training_Dim
A1: Key_Features_ID | B1: Key Features of Teaching
A2: 1 | B2: Remote interaction, live Q&A, and discussions.
A3: 2 | B3: Interactive sessions, group activities.
A4: 3 | B4: Interactive and flexible hybrid model.
A5: 4 | B5: Flexible schedules, learner-driven.
A6: 5 | B6: Real-world application, practical learning.
